{"id": "39265572", "link": "https://batdongsan.com.vn/ban-can-ho-chung-cu-xa-duong-xa-prj-vinhomes-ocean-park-gia-lam/-tot-nhat-thang-3-tai-vinmes-san-so-o-dich-pr39265572", "title": "Căn hộ chung cư giá tốt nhất tháng 4 tại Vinhomes Ocean Park - sẵn sổ giao dịch", "desc": "Em gửi Quý Anh, Chị đang có nhu cầu mua căn hộ chung cư Vinhomes Ocean Park với nhu cầu để ở, đầu tư dòng tiền tham khảo quỹ căn hộ chung cư giá tốt, thực tế tại dự án. Call/Sms/Zalo em để ra đề bài em sẽ có lời giải phù hợp nhất tới Anh, Chị.\n0941 939 ***\n.\n\n+ Căn hộ Studio 28m², tầng 25, hướng mát, full nội thất, phân khu S2: 1,19 tỷ đồng.\n+ Căn hộ 1 phòng ngủ 43m², tầng 9 view thoáng, full nội thất, phân khu S2: 1,595 tỷ đồng.\n+ Căn hộ 2 ngủ 1 vệ sinh, tầng 15 view thoáng, full nội thất, phân khu S1: 1,9 tỷ đồng.\n+ Căn hộ 2 ngủ 2 vệ sinh, tầng 5 view thoáng, đồ cơ bản, phân khu S2: 2,11 tỷ đồng.\n+ Căn hộ 2 ngủ 2 vệ sinh góc, tầng 16 view thoáng, hướng mát, đồ cơ bản phân khu S1: 2,35 tỷ đồng.\n+ Căn hộ 3 phòng ngủ, tầng 20 view thoáng, nguyên bản, phân khu S2: 2,7 tỷ đồng.\n+ Căn hộ Studio 28m², tầng 18 hướng Tây Bắc, phân khu P: 1,26 tỷ đồng.\n+ Căn hộ 2 ngủ 2 vệ sinh, tầng 28 hướng Đông Nam, phân khu P: 2,42 tỷ đồng.\n+ Căn hộ 3 ngủ 87m² tầng 9 hướng Đông Nam, phân khu P: 3,62 tỷ đồng.\n\nNgoài ra, đơn vị em còn rất nhiều quỹ căn hộ khác giá tốt, chủ nhà đang gửi bán, luôn sẵn sàng tư vấn tới anh chị 24/7 qua Hotline\n0941 939 ***\n.\n\n+ Hỗ trợ khách hàng tìm căn hộ chung cư Vinhomes Ocean Park theo đúng tiêu chí khách hàng yêu cầu.\n+ Các căn hộ luôn được tư vấn thủ tục, kiểm tra pháp lý để giao dịch được an toàn và bảo đảm nhất.\n+ Liên kết và hiểu cặn kẽ 100% thủ tục vay vốn ngân hàng: BIDV, Techcombank, Vietcombank, ACB,\n+ Hỗ trợ khách hàng tận tâm từ A - Z cho đến khi hoàn tất 100% thủ tục chuyển nhượng.", "price": null, "project": {"name": "Vinhomes Ocean Park Gia Lâm", "desc": null, "investor": "Văn phòng", "status": null}, "cus_attr": [{"Diện tích": "64 m²"}, {"Mức giá": "2,1 tỷ"}, {"Số phòng ngủ": "2 phòng"}, {"Số toilet": "2 phòng"}, {"Pháp lý": "Sổ đỏ/ Sổ hồng"}, {"Nội thất": "Đầy đủ"}], "contact": {"name": "Đại Hiệp", "mobile": "0941939988", "email": "vudaihiep1608@gmail.com", "user_id": 1204615}, "address": {"full_add": "Dự án Vinhomes Ocean Park Gia Lâm, Xã Dương Xá, Gia Lâm, Hà Nội", "province_add": null, "district_add": null, "ward_add": null, "street_add": null, "num_add": null, "longitude": null, "latitude": null}, "created_date": "31/03/2024", "expire_date": "10/04/2024", "post_category": "Tin VIP Kim Cương"}